[
  {
    "url": "https://www.huffpost.com/entry/trump-says-navy-will-soon-be-the-largest-since-world-war-i_n_58b88ba6e4b083fe57c2f36b",
    "published_date": "2017-03-02T21:07:03Z",
    "author": "HuffPost Video",
    "title": "Trump Says Navy 'Will Soon Be The Largest' Since World War I",
    "text": "HuffPost Video",
    "month": "2017-03",
    "data$month": "2017-03"
  },
  {
    "url": "https://www.huffpost.com/entry/secretary-tom-price-discusses-tax-credits-on-the-new-healthcare-bill_n_58bf2345e4b041215c9fe4bd",
    "published_date": "2017-03-07T21:07:03Z",
    "author": "HuffPost Video",
    "title": "Secretary Tom Price Discusses Tax Credits On The New Healthcare Bill",
    "text": "HuffPost Video",
    "month": "2017-03",
    "data$month": "2017-03"
  },
  {
    "url": "https://www.huffpost.com/entry/president-trumps-new-tweets-are-causing-a-stir_n_5b4f8b4be4b07de723e94c2c",
    "published_date": "2017-03-06T23:04:40Z",
    "author": "HuffPost Video",
    "title": "President Trump's New Tweets Are Causing A Stir",
    "text": "HuffPost Video",
    "month": "2017-03",
    "data$month": "2017-03"
  },
  {
    "url": "https://www.huffpost.com/entry/rosie-odonnell-gives-speech-outside-of-the-white-house-before-trumps-address-to-congress_n_5b55e19be4b07de723e96014",
    "published_date": "2017-03-01T00:38:28Z",
    "author": "HuffPost Video",
    "title": "Rosie O'Donnell Gives Speech Outside Of The White House Before Trump's Address to Congress",
    "text": "HuffPost Video",
    "month": "2017-03",
    "data$month": "2017-03"
  },
  {
    "url": "https://www.huffpost.com/entry/beauty-and-the-beast-premiere-live_n_58b87689e4b01fc1bde6eb80",
    "published_date": "2017-03-02T22:58:04Z",
    "author": "Ishita Singh",
    "title": "Watch The 'Beauty And The Beast' Premiere Live!",
    "text": "Senior Programming Manager, HuffPost Video",
    "sentiment_val": 0,
    "month": "2017-03",
    "data$month": "2017-03"
  },
  {
    "url": "https://www.huffpost.com/entry/schwarzenegger-out-as-celebrity-apprentice-host_n_58ba028de4b098048878d7e9",
    "published_date": "2017-03-03T23:47:03Z",
    "author": "HuffPost Video",
    "title": "Schwarzenegger Out As 'Celebrity Apprentice' Host",
    "text": "HuffPost Video",
    "month": "2017-03",
    "data$month": "2017-03"
  },
  {
    "url": "https://www.huffpost.com/entry/donald-trump-may-donate-salary-to-charity-of-press-corps-choice-says-spicer_n_58c6df21e4b092b4003960fd",
    "published_date": "2017-03-13T17:47:04Z",
    "author": "HuffPost Video",
    "title": "Donald Trump May Donate Salary To Charity Of Press Corps' Choice, Says Spicer",
    "text": "HuffPost Video",
    "month": "2017-03",
    "data$month": "2017-03"
  }
]
